Metadata-Version: 2.1
Name: kitty-plotnine
Version: 1.2.2
Summary: Plot from the command-line with one-liners. Render plots in-line
Home-page: https://github.com/talwrii/kitty-plotnine
Author: @readwithai
Author-email: talwrii@gmail.com
License: GPLv3
Keywords: kitty,terminal,plot,plotting
